cifrum/__init__.py
cifrum/_index/__init__.py
cifrum/_index/okid10.py
cifrum/_instance.py
cifrum/_portfolio/__init__.py
cifrum/_portfolio/currency.py
cifrum/_portfolio/portfolio.py
cifrum/_search.py
cifrum/_settings.py
cifrum/_sources/__init__.py
cifrum/_sources/all_sources.py
cifrum/_sources/base_classes.py
cifrum/_sources/inflation_source.py
cifrum/_sources/micex_stocks_source.py
cifrum/_sources/moex_indexes_source.py
cifrum/_sources/mutru_funds_source.py
cifrum/_sources/okama_source.py
cifrum/_sources/registries.py
cifrum/_sources/single_financial_symbol_source.py
cifrum/_sources/us_data_source.py
cifrum/_sources/yahoo_indexes_source.py
cifrum/common/__init__.py
cifrum/common/enums.py
cifrum/common/financial_symbol.py
cifrum/common/financial_symbol_id.py
cifrum/common/financial_symbol_info.py
cifrum/common/time_series.py
cifrum-0.2.6.dist-info/LICENSE
cifrum-0.2.6.dist-info/WHEEL
cifrum-0.2.6.dist-info/METADATA
cifrum-0.2.6.dist-info/RECORD
