Metadata-Version: 2.1
Name: cifrum
Version: 0.2.6
Summary: Flexible and easy-to-use Python library for analysis & manipulation with financial & economic data
Home-page: https://github.com/okama-io/cifrum
Keywords: Modern portfolio theory,Financial library,Asset allocation,Portfolio investments,Financial operations,Financial analysys,Quantitative finance
Author: Alexander Myltsev
Requires-Python: >=3.6,<4.0
Classifier: Development Status :: 3 - Alpha
Classifier: Framework :: IPython
Classifier: Framework :: Jupyter
Classifier: Intended Audience :: Developers
Classifier: Intended Audience :: End Users/Desktop
Classifier: Intended Audience :: Financial and Insurance Industry
Classifier: License :: OSI Approved :: MIT License
Classifier: Programming Language :: Python
Classifier: Programming Language :: Python :: 3
Classifier: Programming Language :: Python :: 3 :: Only
Classifier: Programming Language :: Python :: 3.6
Classifier: Programming Language :: Python :: 3.7
Classifier: Programming Language :: Python :: 3.8
Classifier: Topic :: Office/Business :: Financial
Classifier: Topic :: Office/Business :: Financial :: Investment
Classifier: Topic :: Scientific/Engineering :: Information Analysis
Classifier: Topic :: Software Development :: Libraries
Classifier: Typing :: Typed
Requires-Dist: PyContracts (>=1.8,<2.0)
Requires-Dist: numpy (>=1.16,<2.0)
Requires-Dist: pandas (>=0.24,<0.25)
Requires-Dist: pinject (>=0.14.1,<0.15.0)
Requires-Dist: typing_extensions (>=3.7,<4.0)
Project-URL: Repository, https://github.com/okama-io/cifrum
